{
  "item/acacia_boat": [
    0,
    0,
    16,
    16
  ],
  "item/acacia_chest_boat": [
    16,
    0,
    16,
    16
  ],
  "item/acacia_door": [
    32,
    0,
    16,
    16
  ],
  "item/acacia_hanging_sign": [
    48,
    0,
    16,
    16
  ],
  "item/acacia_sign": [
    64,
    0,
    16,
    16
  ],
  "item/amethyst_shard": [
    80,
    0,
    16,
    16
  ],
  "item/angler_pottery_sherd": [
    96,
    0,
    16,
    16
  ],
  "item/apple": [
    112,
    0,
    16,
    16
  ],
  "item/archer_pottery_sherd": [
    128,
    0,
    16,
    16
  ],
  "item/armadillo_scute": [
    144,
    0,
    16,
    16
  ],
  "item/armor_stand": [
    160,
    0,
    16,
    16
  ],
  "item/arms_up_pottery_sherd": [
    176,
    0,
    16,
    16
  ],
  "item/arrow": [
    192,
    0,
    16,
    16
  ],
  "item/axolotl_bucket": [
    208,
    0,
    16,
    16
  ],
  "item/baked_potato": [
    224,
    0,
    16,
    16
  ],
  "item/bamboo": [
    240,
    0,
    16,
    16
  ],
  "item/bamboo_chest_raft": [
    256,
    0,
    16,
    16
  ],
  "item/bamboo_door": [
    272,
    0,
    16,
    16
  ],
  "item/bamboo_hanging_sign": [
    288,
    0,
    16,
    16
  ],
  "item/bamboo_raft": [
    304,
    0,
    16,
    16
  ],
  "item/bamboo_sign": [
    320,
    0,
    16,
    16
  ],
  "item/barrier": [
    336,
    0,
    16,
    16
  ],
  "item/beef": [
    352,
    0,
    16,
    16
  ],
  "item/beetroot": [
    368,
    0,
    16,
    16
  ],
  "item/beetroot_seeds": [
    384,
    0,
    16,
    16
  ],
  "item/beetroot_soup": [
    400,
    0,
    16,
    16
  ],
  "item/bell": [
    416,
    0,
    16,
    16
  ],
  "item/birch_boat": [
    432,
    0,
    16,
    16
  ],
  "item/birch_chest_boat": [
    448,
    0,
    16,
    16
  ],
  "item/birch_door": [
    464,
    0,
    16,
    16
  ],
  "item/birch_hanging_sign": [
    480,
    0,
    16,
    16
  ],
  "item/birch_sign": [
    496,
    0,
    16,
    16
  ],
  "item/black_candle": [
    0,
    16,
    16,
    16
  ],
  "item/black_dye": [
    16,
    16,
    16,
    16
  ],
  "item/blade_pottery_sherd": [
    32,
    16,
    16,
    16
  ],
  "item/blaze_powder": [
    48,
    16,
    16,
    16
  ],
  "item/blaze_rod": [
    64,
    16,
    16,
    16
  ],
  "item/blue_candle": [
    80,
    16,
    16,
    16
  ],
  "item/blue_dye": [
    96,
    16,
    16,
    16
  ],
  "item/bolt_armor_trim_smithing_template": [
    112,
    16,
    16,
    16
  ],
  "item/bone": [
    128,
    16,
    16,
    16
  ],
  "item/bone_meal": [
    144,
    16,
    16,
    16
  ],
  "item/book": [
    160,
    16,
    16,
    16
  ],
  "item/bow": [
    176,
    16,
    16,
    16
  ],
  "item/bowl": [
    192,
    16,
    16,
    16
  ],
  "item/bow_pulling_0": [
    208,
    16,
    16,
    16
  ],
  "item/bow_pulling_1": [
    224,
    16,
    16,
    16
  ],
  "item/bow_pulling_2": [
    240,
    16,
    16,
    16
  ],
  "item/bread": [
    256,
    16,
    16,
    16
  ],
  "item/breeze_rod": [
    272,
    16,
    16,
    16
  ],
  "item/brewer_pottery_sherd": [
    288,
    16,
    16,
    16
  ],
  "item/brewing_stand": [
    304,
    16,
    16,
    16
  ],
  "item/brick": [
    320,
    16,
    16,
    16
  ],
  "item/broken_elytra": [
    336,
    16,
    16,
    16
  ],
  "item/brown_candle": [
    352,
    16,
    16,
    16
  ],
  "item/brown_dye": [
    368,
    16,
    16,
    16
  ],
  "item/brush": [
    384,
    16,
    16,
    16
  ],
  "item/bucket": [
    400,
    16,
    16,
    16
  ],
  "item/bundle": [
    416,
    16,
    16,
    16
  ],
  "item/bundle_filled": [
    432,
    16,
    16,
    16
  ],
  "item/burn_pottery_sherd": [
    448,
    16,
    16,
    16
  ],
  "item/cake": [
    464,
    16,
    16,
    16
  ],
  "item/campfire": [
    480,
    16,
    16,
    16
  ],
  "item/candle": [
    496,
    16,
    16,
    16
  ],
  "item/carrot": [
    0,
    32,
    16,
    16
  ],
  "item/carrot_on_a_stick": [
    16,
    32,
    16,
    16
  ],
  "item/cauldron": [
    32,
    32,
    16,
    16
  ],
  "item/chain": [
    48,
    32,
    16,
    16
  ],
  "item/chainmail_boots": [
    64,
    32,
    16,
    16
  ],
  "item/chainmail_chestplate": [
    80,
    32,
    16,
    16
  ],
  "item/chainmail_helmet": [
    96,
    32,
    16,
    16
  ],
  "item/chainmail_leggings": [
    112,
    32,
    16,
    16
  ],
  "item/charcoal": [
    128,
    32,
    16,
    16
  ],
  "item/cherry_boat": [
    144,
    32,
    16,
    16
  ],
  "item/cherry_chest_boat": [
    160,
    32,
    16,
    16
  ],
  "item/cherry_door": [
    176,
    32,
    16,
    16
  ],
  "item/cherry_hanging_sign": [
    192,
    32,
    16,
    16
  ],
  "item/cherry_sign": [
    208,
    32,
    16,
    16
  ],
  "item/chest_minecart": [
    224,
    32,
    16,
    16
  ],
  "item/chicken": [
    240,
    32,
    16,
    16
  ],
  "item/chorus_fruit": [
    256,
    32,
    16,
    16
  ],
  "item/clay_ball": [
    272,
    32,
    16,
    16
  ],
  "item/clock_00": [
    288,
    32,
    16,
    16
  ],
  "item/clock_01": [
    304,
    32,
    16,
    16
  ],
  "item/clock_02": [
    320,
    32,
    16,
    16
  ],
  "item/clock_03": [
    336,
    32,
    16,
    16
  ],
  "item/clock_04": [
    352,
    32,
    16,
    16
  ],
  "item/clock_05": [
    368,
    32,
    16,
    16
  ],
  "item/clock_06": [
    384,
    32,
    16,
    16
  ],
  "item/clock_07": [
    400,
    32,
    16,
    16
  ],
  "item/clock_08": [
    416,
    32,
    16,
    16
  ],
  "item/clock_09": [
    432,
    32,
    16,
    16
  ],
  "item/clock_10": [
    448,
    32,
    16,
    16
  ],
  "item/clock_11": [
    464,
    32,
    16,
    16
  ],
  "item/clock_12": [
    480,
    32,
    16,
    16
  ],
  "item/clock_13": [
    496,
    32,
    16,
    16
  ],
  "item/clock_14": [
    0,
    48,
    16,
    16
  ],
  "item/clock_15": [
    16,
    48,
    16,
    16
  ],
  "item/clock_16": [
    32,
    48,
    16,
    16
  ],
  "item/clock_17": [
    48,
    48,
    16,
    16
  ],
  "item/clock_18": [
    64,
    48,
    16,
    16
  ],
  "item/clock_19": [
    80,
    48,
    16,
    16
  ],
  "item/clock_20": [
    96,
    48,
    16,
    16
  ],
  "item/clock_21": [
    112,
    48,
    16,
    16
  ],
  "item/clock_22": [
    128,
    48,
    16,
    16
  ],
  "item/clock_23": [
    144,
    48,
    16,
    16
  ],
  "item/clock_24": [
    160,
    48,
    16,
    16
  ],
  "item/clock_25": [
    176,
    48,
    16,
    16
  ],
  "item/clock_26": [
    192,
    48,
    16,
    16
  ],
  "item/clock_27": [
    208,
    48,
    16,
    16
  ],
  "item/clock_28": [
    224,
    48,
    16,
    16
  ],
  "item/clock_29": [
    240,
    48,
    16,
    16
  ],
  "item/clock_30": [
    256,
    48,
    16,
    16
  ],
  "item/clock_31": [
    272,
    48,
    16,
    16
  ],
  "item/clock_32": [
    288,
    48,
    16,
    16
  ],
  "item/clock_33": [
    304,
    48,
    16,
    16
  ],
  "item/clock_34": [
    320,
    48,
    16,
    16
  ],
  "item/clock_35": [
    336,
    48,
    16,
    16
  ],
  "item/clock_36": [
    352,
    48,
    16,
    16
  ],
  "item/clock_37": [
    368,
    48,
    16,
    16
  ],
  "item/clock_38": [
    384,
    48,
    16,
    16
  ],
  "item/clock_39": [
    400,
    48,
    16,
    16
  ],
  "item/clock_40": [
    416,
    48,
    16,
    16
  ],
  "item/clock_41": [
    432,
    48,
    16,
    16
  ],
  "item/clock_42": [
    448,
    48,
    16,
    16
  ],
  "item/clock_43": [
    464,
    48,
    16,
    16
  ],
  "item/clock_44": [
    480,
    48,
    16,
    16
  ],
  "item/clock_45": [
    496,
    48,
    16,
    16
  ],
  "item/clock_46": [
    0,
    64,
    16,
    16
  ],
  "item/clock_47": [
    16,
    64,
    16,
    16
  ],
  "item/clock_48": [
    32,
    64,
    16,
    16
  ],
  "item/clock_49": [
    48,
    64,
    16,
    16
  ],
  "item/clock_50": [
    64,
    64,
    16,
    16
  ],
  "item/clock_51": [
    80,
    64,
    16,
    16
  ],
  "item/clock_52": [
    96,
    64,
    16,
    16
  ],
  "item/clock_53": [
    112,
    64,
    16,
    16
  ],
  "item/clock_54": [
    128,
    64,
    16,
    16
  ],
  "item/clock_55": [
    144,
    64,
    16,
    16
  ],
  "item/clock_56": [
    160,
    64,
    16,
    16
  ],
  "item/clock_57": [
    176,
    64,
    16,
    16
  ],
  "item/clock_58": [
    192,
    64,
    16,
    16
  ],
  "item/clock_59": [
    208,
    64,
    16,
    16
  ],
  "item/clock_60": [
    224,
    64,
    16,
    16
  ],
  "item/clock_61": [
    240,
    64,
    16,
    16
  ],
  "item/clock_62": [
    256,
    64,
    16,
    16
  ],
  "item/clock_63": [
    272,
    64,
    16,
    16
  ],
  "item/coal": [
    288,
    64,
    16,
    16
  ],
  "item/coast_armor_trim_smithing_template": [
    304,
    64,
    16,
    16
  ],
  "item/cocoa_beans": [
    320,
    64,
    16,
    16
  ],
  "item/cod": [
    336,
    64,
    16,
    16
  ],
  "item/cod_bucket": [
    352,
    64,
    16,
    16
  ],
  "item/command_block_minecart": [
    368,
    64,
    16,
    16
  ],
  "item/comparator": [
    384,
    64,
    16,
    16
  ],
  "item/compass_00": [
    400,
    64,
    16,
    16
  ],
  "item/compass_01": [
    416,
    64,
    16,
    16
  ],
  "item/compass_02": [
    432,
    64,
    16,
    16
  ],
  "item/compass_03": [
    448,
    64,
    16,
    16
  ],
  "item/compass_04": [
    464,
    64,
    16,
    16
  ],
  "item/compass_05": [
    480,
    64,
    16,
    16
  ],
  "item/compass_06": [
    496,
    64,
    16,
    16
  ],
  "item/compass_07": [
    0,
    80,
    16,
    16
  ],
  "item/compass_08": [
    16,
    80,
    16,
    16
  ],
  "item/compass_09": [
    32,
    80,
    16,
    16
  ],
  "item/compass_10": [
    48,
    80,
    16,
    16
  ],
  "item/compass_11": [
    64,
    80,
    16,
    16
  ],
  "item/compass_12": [
    80,
    80,
    16,
    16
  ],
  "item/compass_13": [
    96,
    80,
    16,
    16
  ],
  "item/compass_14": [
    112,
    80,
    16,
    16
  ],
  "item/compass_15": [
    128,
    80,
    16,
    16
  ],
  "item/compass_16": [
    144,
    80,
    16,
    16
  ],
  "item/compass_17": [
    160,
    80,
    16,
    16
  ],
  "item/compass_18": [
    176,
    80,
    16,
    16
  ],
  "item/compass_19": [
    192,
    80,
    16,
    16
  ],
  "item/compass_20": [
    208,
    80,
    16,
    16
  ],
  "item/compass_21": [
    224,
    80,
    16,
    16
  ],
  "item/compass_22": [
    240,
    80,
    16,
    16
  ],
  "item/compass_23": [
    256,
    80,
    16,
    16
  ],
  "item/compass_24": [
    272,
    80,
    16,
    16
  ],
  "item/compass_25": [
    288,
    80,
    16,
    16
  ],
  "item/compass_26": [
    304,
    80,
    16,
    16
  ],
  "item/compass_27": [
    320,
    80,
    16,
    16
  ],
  "item/compass_28": [
    336,
    80,
    16,
    16
  ],
  "item/compass_29": [
    352,
    80,
    16,
    16
  ],
  "item/compass_30": [
    368,
    80,
    16,
    16
  ],
  "item/compass_31": [
    384,
    80,
    16,
    16
  ],
  "item/cooked_beef": [
    400,
    80,
    16,
    16
  ],
  "item/cooked_chicken": [
    416,
    80,
    16,
    16
  ],
  "item/cooked_cod": [
    432,
    80,
    16,
    16
  ],
  "item/cooked_mutton": [
    448,
    80,
    16,
    16
  ],
  "item/cooked_porkchop": [
    464,
    80,
    16,
    16
  ],
  "item/cooked_rabbit": [
    480,
    80,
    16,
    16
  ],
  "item/cooked_salmon": [
    496,
    80,
    16,
    16
  ],
  "item/cookie": [
    0,
    96,
    16,
    16
  ],
  "item/copper_door": [
    16,
    96,
    16,
    16
  ],
  "item/copper_ingot": [
    32,
    96,
    16,
    16
  ],
  "item/creeper_banner_pattern": [
    48,
    96,
    16,
    16
  ],
  "item/crimson_door": [
    64,
    96,
    16,
    16
  ],
  "item/crimson_hanging_sign": [
    80,
    96,
    16,
    16
  ],
  "item/crimson_sign": [
    96,
    96,
    16,
    16
  ],
  "item/crossbow_arrow": [
    112,
    96,
    16,
    16
  ],
  "item/crossbow_firework": [
    128,
    96,
    16,
    16
  ],
  "item/crossbow_pulling_0": [
    144,
    96,
    16,
    16
  ],
  "item/crossbow_pulling_1": [
    160,
    96,
    16,
    16
  ],
  "item/crossbow_pulling_2": [
    176,
    96,
    16,
    16
  ],
  "item/crossbow_standby": [
    192,
    96,
    16,
    16
  ],
  "item/cyan_candle": [
    208,
    96,
    16,
    16
  ],
  "item/cyan_dye": [
    224,
    96,
    16,
    16
  ],
  "item/danger_pottery_sherd": [
    240,
    96,
    16,
    16
  ],
  "item/dark_oak_boat": [
    256,
    96,
    16,
    16
  ],
  "item/dark_oak_chest_boat": [
    272,
    96,
    16,
    16
  ],
  "item/dark_oak_door": [
    288,
    96,
    16,
    16
  ],
  "item/dark_oak_hanging_sign": [
    304,
    96,
    16,
    16
  ],
  "item/dark_oak_sign": [
    320,
    96,
    16,
    16
  ],
  "item/diamond": [
    336,
    96,
    16,
    16
  ],
  "item/diamond_axe": [
    352,
    96,
    16,
    16
  ],
  "item/diamond_boots": [
    368,
    96,
    16,
    16
  ],
  "item/diamond_chestplate": [
    384,
    96,
    16,
    16
  ],
  "item/diamond_helmet": [
    400,
    96,
    16,
    16
  ],
  "item/diamond_hoe": [
    416,
    96,
    16,
    16
  ],
  "item/diamond_horse_armor": [
    432,
    96,
    16,
    16
  ],
  "item/diamond_leggings": [
    448,
    96,
    16,
    16
  ],
  "item/diamond_pickaxe": [
    464,
    96,
    16,
    16
  ],
  "item/diamond_shovel": [
    480,
    96,
    16,
    16
  ],
  "item/diamond_sword": [
    496,
    96,
    16,
    16
  ],
  "item/disc_fragment_5": [
    0,
    112,
    16,
    16
  ],
  "item/dragon_breath": [
    16,
    112,
    16,
    16
  ],
  "item/dried_kelp": [
    32,
    112,
    16,
    16
  ],
  "item/dune_armor_trim_smithing_template": [
    48,
    112,
    16,
    16
  ],
  "item/echo_shard": [
    64,
    112,
    16,
    16
  ],
  "item/egg": [
    80,
    112,
    16,
    16
  ],
  "item/elytra": [
    96,
    112,
    16,
    16
  ],
  "item/emerald": [
    112,
    112,
    16,
    16
  ],
  "item/empty_armor_slot_boots": [
    128,
    112,
    16,
    16
  ],
  "item/empty_armor_slot_chestplate": [
    144,
    112,
    16,
    16
  ],
  "item/empty_armor_slot_helmet": [
    160,
    112,
    16,
    16
  ],
  "item/empty_armor_slot_leggings": [
    176,
    112,
    16,
    16
  ],
  "item/empty_armor_slot_shield": [
    192,
    112,
    16,
    16
  ],
  "item/empty_slot_amethyst_shard": [
    208,
    112,
    16,
    16
  ],
  "item/empty_slot_axe": [
    224,
    112,
    16,
    16
  ],
  "item/empty_slot_diamond": [
    240,
    112,
    16,
    16
  ],
  "item/empty_slot_emerald": [
    256,
    112,
    16,
    16
  ],
  "item/empty_slot_hoe": [
    272,
    112,
    16,
    16
  ],
  "item/empty_slot_ingot": [
    288,
    112,
    16,
    16
  ],
  "item/empty_slot_lapis_lazuli": [
    304,
    112,
    16,
    16
  ],
  "item/empty_slot_pickaxe": [
    320,
    112,
    16,
    16
  ],
  "item/empty_slot_quartz": [
    336,
    112,
    16,
    16
  ],
  "item/empty_slot_redstone_dust": [
    352,
    112,
    16,
    16
  ],
  "item/empty_slot_shovel": [
    368,
    112,
    16,
    16
  ],
  "item/empty_slot_smithing_template_armor_trim": [
    384,
    112,
    16,
    16
  ],
  "item/empty_slot_smithing_template_netherite_upgrade": [
    400,
    112,
    16,
    16
  ],
  "item/empty_slot_sword": [
    416,
    112,
    16,
    16
  ],
  "item/enchanted_book": [
    432,
    112,
    16,
    16
  ],
  "item/ender_eye": [
    448,
    112,
    16,
    16
  ],
  "item/ender_pearl": [
    464,
    112,
    16,
    16
  ],
  "item/end_crystal": [
    480,
    112,
    16,
    16
  ],
  "item/experience_bottle": [
    496,
    112,
    16,
    16
  ],
  "item/explorer_pottery_sherd": [
    0,
    128,
    16,
    16
  ],
  "item/exposed_copper_door": [
    16,
    128,
    16,
    16
  ],
  "item/eye_armor_trim_smithing_template": [
    32,
    128,
    16,
    16
  ],
  "item/feather": [
    48,
    128,
    16,
    16
  ],
  "item/fermented_spider_eye": [
    64,
    128,
    16,
    16
  ],
  "item/filled_map": [
    80,
    128,
    16,
    16
  ],
  "item/filled_map_markings": [
    96,
    128,
    16,
    16
  ],
  "item/firework_rocket": [
    112,
    128,
    16,
    16
  ],
  "item/firework_star": [
    128,
    128,
    16,
    16
  ],
  "item/firework_star_overlay": [
    144,
    128,
    16,
    16
  ],
  "item/fire_charge": [
    160,
    128,
    16,
    16
  ],
  "item/fishing_rod": [
    176,
    128,
    16,
    16
  ],
  "item/fishing_rod_cast": [
    192,
    128,
    16,
    16
  ],
  "item/flint": [
    208,
    128,
    16,
    16
  ],
  "item/flint_and_steel": [
    224,
    128,
    16,
    16
  ],
  "item/flower_banner_pattern": [
    240,
    128,
    16,
    16
  ],
  "item/flower_pot": [
    256,
    128,
    16,
    16
  ],
  "item/flow_armor_trim_smithing_template": [
    272,
    128,
    16,
    16
  ],
  "item/flow_banner_pattern": [
    288,
    128,
    16,
    16
  ],
  "item/flow_pottery_sherd": [
    304,
    128,
    16,
    16
  ],
  "item/friend_pottery_sherd": [
    320,
    128,
    16,
    16
  ],
  "item/furnace_minecart": [
    336,
    128,
    16,
    16
  ],
  "item/ghast_tear": [
    352,
    128,
    16,
    16
  ],
  "item/glass_bottle": [
    368,
    128,
    16,
    16
  ],
  "item/glistering_melon_slice": [
    384,
    128,
    16,
    16
  ],
  "item/globe_banner_pattern": [
    400,
    128,
    16,
    16
  ],
  "item/glowstone_dust": [
    416,
    128,
    16,
    16
  ],
  "item/glow_berries": [
    432,
    128,
    16,
    16
  ],
  "item/glow_ink_sac": [
    448,
    128,
    16,
    16
  ],
  "item/glow_item_frame": [
    464,
    128,
    16,
    16
  ],
  "item/goat_horn": [
    480,
    128,
    16,
    16
  ],
  "item/golden_apple": [
    496,
    128,
    16,
    16
  ],
  "item/golden_axe": [
    0,
    144,
    16,
    16
  ],
  "item/golden_boots": [
    16,
    144,
    16,
    16
  ],
  "item/golden_carrot": [
    32,
    144,
    16,
    16
  ],
  "item/golden_chestplate": [
    48,
    144,
    16,
    16
  ],
  "item/golden_helmet": [
    64,
    144,
    16,
    16
  ],
  "item/golden_hoe": [
    80,
    144,
    16,
    16
  ],
  "item/golden_horse_armor": [
    96,
    144,
    16,
    16
  ],
  "item/golden_leggings": [
    112,
    144,
    16,
    16
  ],
  "item/golden_pickaxe": [
    128,
    144,
    16,
    16
  ],
  "item/golden_shovel": [
    144,
    144,
    16,
    16
  ],
  "item/golden_sword": [
    160,
    144,
    16,
    16
  ],
  "item/gold_ingot": [
    176,
    144,
    16,
    16
  ],
  "item/gold_nugget": [
    192,
    144,
    16,
    16
  ],
  "item/gray_candle": [
    208,
    144,
    16,
    16
  ],
  "item/gray_dye": [
    224,
    144,
    16,
    16
  ],
  "item/green_candle": [
    240,
    144,
    16,
    16
  ],
  "item/green_dye": [
    256,
    144,
    16,
    16
  ],
  "item/gunpowder": [
    272,
    144,
    16,
    16
  ],
  "item/guster_banner_pattern": [
    288,
    144,
    16,
    16
  ],
  "item/guster_pottery_sherd": [
    304,
    144,
    16,
    16
  ],
  "item/heartbreak_pottery_sherd": [
    320,
    144,
    16,
    16
  ],
  "item/heart_of_the_sea": [
    336,
    144,
    16,
    16
  ],
  "item/heart_pottery_sherd": [
    352,
    144,
    16,
    16
  ],
  "item/honeycomb": [
    368,
    144,
    16,
    16
  ],
  "item/honey_bottle": [
    384,
    144,
    16,
    16
  ],
  "item/hopper": [
    400,
    144,
    16,
    16
  ],
  "item/hopper_minecart": [
    416,
    144,
    16,
    16
  ],
  "item/host_armor_trim_smithing_template": [
    432,
    144,
    16,
    16
  ],
  "item/howl_pottery_sherd": [
    448,
    144,
    16,
    16
  ],
  "item/ink_sac": [
    464,
    144,
    16,
    16
  ],
  "item/iron_axe": [
    480,
    144,
    16,
    16
  ],
  "item/iron_boots": [
    496,
    144,
    16,
    16
  ],
  "item/iron_chestplate": [
    0,
    160,
    16,
    16
  ],
  "item/iron_door": [
    16,
    160,
    16,
    16
  ],
  "item/iron_helmet": [
    32,
    160,
    16,
    16
  ],
  "item/iron_hoe": [
    48,
    160,
    16,
    16
  ],
  "item/iron_horse_armor": [
    64,
    160,
    16,
    16
  ],
  "item/iron_ingot": [
    80,
    160,
    16,
    16
  ],
  "item/iron_leggings": [
    96,
    160,
    16,
    16
  ],
  "item/iron_nugget": [
    112,
    160,
    16,
    16
  ],
  "item/iron_pickaxe": [
    128,
    160,
    16,
    16
  ],
  "item/iron_shovel": [
    144,
    160,
    16,
    16
  ],
  "item/iron_sword": [
    160,
    160,
    16,
    16
  ],
  "item/item_frame": [
    176,
    160,
    16,
    16
  ],
  "item/jungle_boat": [
    192,
    160,
    16,
    16
  ],
  "item/jungle_chest_boat": [
    208,
    160,
    16,
    16
  ],
  "item/jungle_door": [
    224,
    160,
    16,
    16
  ],
  "item/jungle_hanging_sign": [
    240,
    160,
    16,
    16
  ],
  "item/jungle_sign": [
    256,
    160,
    16,
    16
  ],
  "item/kelp": [
    272,
    160,
    16,
    16
  ],
  "item/knowledge_book": [
    288,
    160,
    16,
    16
  ],
  "item/lantern": [
    304,
    160,
    16,
    16
  ],
  "item/lapis_lazuli": [
    320,
    160,
    16,
    16
  ],
  "item/lava_bucket": [
    336,
    160,
    16,
    16
  ],
  "item/lead": [
    352,
    160,
    16,
    16
  ],
  "item/leather": [
    368,
    160,
    16,
    16
  ],
  "item/leather_boots": [
    384,
    160,
    16,
    16
  ],
  "item/leather_boots_overlay": [
    400,
    160,
    16,
    16
  ],
  "item/leather_chestplate": [
    416,
    160,
    16,
    16
  ],
  "item/leather_chestplate_overlay": [
    432,
    160,
    16,
    16
  ],
  "item/leather_helmet": [
    448,
    160,
    16,
    16
  ],
  "item/leather_helmet_overlay": [
    464,
    160,
    16,
    16
  ],
  "item/leather_horse_armor": [
    480,
    160,
    16,
    16
  ],
  "item/leather_leggings": [
    496,
    160,
    16,
    16
  ],
  "item/leather_leggings_overlay": [
    0,
    176,
    16,
    16
  ],
  "item/light": [
    16,
    176,
    16,
    16
  ],
  "item/light_00": [
    32,
    176,
    16,
    16
  ],
  "item/light_01": [
    48,
    176,
    16,
    16
  ],
  "item/light_02": [
    64,
    176,
    16,
    16
  ],
  "item/light_03": [
    80,
    176,
    16,
    16
  ],
  "item/light_04": [
    96,
    176,
    16,
    16
  ],
  "item/light_05": [
    112,
    176,
    16,
    16
  ],
  "item/light_06": [
    128,
    176,
    16,
    16
  ],
  "item/light_07": [
    144,
    176,
    16,
    16
  ],
  "item/light_08": [
    160,
    176,
    16,
    16
  ],
  "item/light_09": [
    176,
    176,
    16,
    16
  ],
  "item/light_10": [
    192,
    176,
    16,
    16
  ],
  "item/light_11": [
    208,
    176,
    16,
    16
  ],
  "item/light_12": [
    224,
    176,
    16,
    16
  ],
  "item/light_13": [
    240,
    176,
    16,
    16
  ],
  "item/light_14": [
    256,
    176,
    16,
    16
  ],
  "item/light_15": [
    272,
    176,
    16,
    16
  ],
  "item/light_blue_candle": [
    288,
    176,
    16,
    16
  ],
  "item/light_blue_dye": [
    304,
    176,
    16,
    16
  ],
  "item/light_gray_candle": [
    320,
    176,
    16,
    16
  ],
  "item/light_gray_dye": [
    336,
    176,
    16,
    16
  ],
  "item/lime_candle": [
    352,
    176,
    16,
    16
  ],
  "item/lime_dye": [
    368,
    176,
    16,
    16
  ],
  "item/lingering_potion": [
    384,
    176,
    16,
    16
  ],
  "item/mace": [
    400,
    176,
    16,
    16
  ],
  "item/magenta_candle": [
    416,
    176,
    16,
    16
  ],
  "item/magenta_dye": [
    432,
    176,
    16,
    16
  ],
  "item/magma_cream": [
    448,
    176,
    16,
    16
  ],
  "item/mangrove_boat": [
    464,
    176,
    16,
    16
  ],
  "item/mangrove_chest_boat": [
    480,
    176,
    16,
    16
  ],
  "item/mangrove_door": [
    496,
    176,
    16,
    16
  ],
  "item/mangrove_hanging_sign": [
    0,
    192,
    16,
    16
  ],
  "item/mangrove_propagule": [
    16,
    192,
    16,
    16
  ],
  "item/mangrove_sign": [
    32,
    192,
    16,
    16
  ],
  "item/map": [
    48,
    192,
    16,
    16
  ],
  "item/melon_seeds": [
    64,
    192,
    16,
    16
  ],
  "item/melon_slice": [
    80,
    192,
    16,
    16
  ],
  "item/milk_bucket": [
    96,
    192,
    16,
    16
  ],
  "item/minecart": [
    112,
    192,
    16,
    16
  ],
  "item/miner_pottery_sherd": [
    128,
    192,
    16,
    16
  ],
  "item/mojang_banner_pattern": [
    144,
    192,
    16,
    16
  ],
  "item/mourner_pottery_sherd": [
    160,
    192,
    16,
    16
  ],
  "item/mushroom_stew": [
    176,
    192,
    16,
    16
  ],
  "item/music_disc_11": [
    192,
    192,
    16,
    16
  ],
  "item/music_disc_13": [
    208,
    192,
    16,
    16
  ],
  "item/music_disc_5": [
    224,
    192,
    16,
    16
  ],
  "item/music_disc_blocks": [
    240,
    192,
    16,
    16
  ],
  "item/music_disc_cat": [
    256,
    192,
    16,
    16
  ],
  "item/music_disc_chirp": [
    272,
    192,
    16,
    16
  ],
  "item/music_disc_creator": [
    288,
    192,
    16,
    16
  ],
  "item/music_disc_creator_music_box": [
    304,
    192,
    16,
    16
  ],
  "item/music_disc_far": [
    320,
    192,
    16,
    16
  ],
  "item/music_disc_mall": [
    336,
    192,
    16,
    16
  ],
  "item/music_disc_mellohi": [
    352,
    192,
    16,
    16
  ],
  "item/music_disc_otherside": [
    368,
    192,
    16,
    16
  ],
  "item/music_disc_pigstep": [
    384,
    192,
    16,
    16
  ],
  "item/music_disc_precipice": [
    400,
    192,
    16,
    16
  ],
  "item/music_disc_relic": [
    416,
    192,
    16,
    16
  ],
  "item/music_disc_stal": [
    432,
    192,
    16,
    16
  ],
  "item/music_disc_strad": [
    448,
    192,
    16,
    16
  ],
  "item/music_disc_wait": [
    464,
    192,
    16,
    16
  ],
  "item/music_disc_ward": [
    480,
    192,
    16,
    16
  ],
  "item/mutton": [
    496,
    192,
    16,
    16
  ],
  "item/name_tag": [
    0,
    208,
    16,
    16
  ],
  "item/nautilus_shell": [
    16,
    208,
    16,
    16
  ],
  "item/netherite_axe": [
    32,
    208,
    16,
    16
  ],
  "item/netherite_boots": [
    48,
    208,
    16,
    16
  ],
  "item/netherite_chestplate": [
    64,
    208,
    16,
    16
  ],
  "item/netherite_helmet": [
    80,
    208,
    16,
    16
  ],
  "item/netherite_hoe": [
    96,
    208,
    16,
    16
  ],
  "item/netherite_ingot": [
    112,
    208,
    16,
    16
  ],
  "item/netherite_leggings": [
    128,
    208,
    16,
    16
  ],
  "item/netherite_pickaxe": [
    144,
    208,
    16,
    16
  ],
  "item/netherite_scrap": [
    160,
    208,
    16,
    16
  ],
  "item/netherite_shovel": [
    176,
    208,
    16,
    16
  ],
  "item/netherite_sword": [
    192,
    208,
    16,
    16
  ],
  "item/netherite_upgrade_smithing_template": [
    208,
    208,
    16,
    16
  ],
  "item/nether_brick": [
    224,
    208,
    16,
    16
  ],
  "item/nether_sprouts": [
    240,
    208,
    16,
    16
  ],
  "item/nether_star": [
    256,
    208,
    16,
    16
  ],
  "item/nether_wart": [
    272,
    208,
    16,
    16
  ],
  "item/oak_boat": [
    288,
    208,
    16,
    16
  ],
  "item/oak_chest_boat": [
    304,
    208,
    16,
    16
  ],
  "item/oak_door": [
    320,
    208,
    16,
    16
  ],
  "item/oak_hanging_sign": [
    336,
    208,
    16,
    16
  ],
  "item/oak_sign": [
    352,
    208,
    16,
    16
  ],
  "item/ominous_bottle": [
    368,
    208,
    16,
    16
  ],
  "item/ominous_trial_key": [
    384,
    208,
    16,
    16
  ],
  "item/orange_candle": [
    400,
    208,
    16,
    16
  ],
  "item/orange_dye": [
    416,
    208,
    16,
    16
  ],
  "item/oxidized_copper_door": [
    432,
    208,
    16,
    16
  ],
  "item/painting": [
    448,
    208,
    16,
    16
  ],
  "item/paper": [
    464,
    208,
    16,
    16
  ],
  "item/phantom_membrane": [
    480,
    208,
    16,
    16
  ],
  "item/piglin_banner_pattern": [
    496,
    208,
    16,
    16
  ],
  "item/pink_candle": [
    0,
    224,
    16,
    16
  ],
  "item/pink_dye": [
    16,
    224,
    16,
    16
  ],
  "item/pink_petals": [
    32,
    224,
    16,
    16
  ],
  "item/pitcher_plant": [
    48,
    224,
    16,
    16
  ],
  "item/pitcher_pod": [
    64,
    224,
    16,
    16
  ],
  "item/plenty_pottery_sherd": [
    80,
    224,
    16,
    16
  ],
  "item/pointed_dripstone": [
    96,
    224,
    16,
    16
  ],
  "item/poisonous_potato": [
    112,
    224,
    16,
    16
  ],
  "item/popped_chorus_fruit": [
    128,
    224,
    16,
    16
  ],
  "item/porkchop": [
    144,
    224,
    16,
    16
  ],
  "item/potato": [
    160,
    224,
    16,
    16
  ],
  "item/potion": [
    176,
    224,
    16,
    16
  ],
  "item/potion_overlay": [
    192,
    224,
    16,
    16
  ],
  "item/powder_snow_bucket": [
    208,
    224,
    16,
    16
  ],
  "item/prismarine_crystals": [
    224,
    224,
    16,
    16
  ],
  "item/prismarine_shard": [
    240,
    224,
    16,
    16
  ],
  "item/prize_pottery_sherd": [
    256,
    224,
    16,
    16
  ],
  "item/pufferfish": [
    272,
    224,
    16,
    16
  ],
  "item/pufferfish_bucket": [
    288,
    224,
    16,
    16
  ],
  "item/pumpkin_pie": [
    304,
    224,
    16,
    16
  ],
  "item/pumpkin_seeds": [
    320,
    224,
    16,
    16
  ],
  "item/purple_candle": [
    336,
    224,
    16,
    16
  ],
  "item/purple_dye": [
    352,
    224,
    16,
    16
  ],
  "item/quartz": [
    368,
    224,
    16,
    16
  ],
  "item/rabbit": [
    384,
    224,
    16,
    16
  ],
  "item/rabbit_foot": [
    400,
    224,
    16,
    16
  ],
  "item/rabbit_hide": [
    416,
    224,
    16,
    16
  ],
  "item/rabbit_stew": [
    432,
    224,
    16,
    16
  ],
  "item/raiser_armor_trim_smithing_template": [
    448,
    224,
    16,
    16
  ],
  "item/raw_copper": [
    464,
    224,
    16,
    16
  ],
  "item/raw_gold": [
    480,
    224,
    16,
    16
  ],
  "item/raw_iron": [
    496,
    224,
    16,
    16
  ],
  "item/recovery_compass_00": [
    0,
    240,
    16,
    16
  ],
  "item/recovery_compass_01": [
    16,
    240,
    16,
    16
  ],
  "item/recovery_compass_02": [
    32,
    240,
    16,
    16
  ],
  "item/recovery_compass_03": [
    48,
    240,
    16,
    16
  ],
  "item/recovery_compass_04": [
    64,
    240,
    16,
    16
  ],
  "item/recovery_compass_05": [
    80,
    240,
    16,
    16
  ],
  "item/recovery_compass_06": [
    96,
    240,
    16,
    16
  ],
  "item/recovery_compass_07": [
    112,
    240,
    16,
    16
  ],
  "item/recovery_compass_08": [
    128,
    240,
    16,
    16
  ],
  "item/recovery_compass_09": [
    144,
    240,
    16,
    16
  ],
  "item/recovery_compass_10": [
    160,
    240,
    16,
    16
  ],
  "item/recovery_compass_11": [
    176,
    240,
    16,
    16
  ],
  "item/recovery_compass_12": [
    192,
    240,
    16,
    16
  ],
  "item/recovery_compass_13": [
    208,
    240,
    16,
    16
  ],
  "item/recovery_compass_14": [
    224,
    240,
    16,
    16
  ],
  "item/recovery_compass_15": [
    240,
    240,
    16,
    16
  ],
  "item/recovery_compass_16": [
    256,
    240,
    16,
    16
  ],
  "item/recovery_compass_17": [
    272,
    240,
    16,
    16
  ],
  "item/recovery_compass_18": [
    288,
    240,
    16,
    16
  ],
  "item/recovery_compass_19": [
    304,
    240,
    16,
    16
  ],
  "item/recovery_compass_20": [
    320,
    240,
    16,
    16
  ],
  "item/recovery_compass_21": [
    336,
    240,
    16,
    16
  ],
  "item/recovery_compass_22": [
    352,
    240,
    16,
    16
  ],
  "item/recovery_compass_23": [
    368,
    240,
    16,
    16
  ],
  "item/recovery_compass_24": [
    384,
    240,
    16,
    16
  ],
  "item/recovery_compass_25": [
    400,
    240,
    16,
    16
  ],
  "item/recovery_compass_26": [
    416,
    240,
    16,
    16
  ],
  "item/recovery_compass_27": [
    432,
    240,
    16,
    16
  ],
  "item/recovery_compass_28": [
    448,
    240,
    16,
    16
  ],
  "item/recovery_compass_29": [
    464,
    240,
    16,
    16
  ],
  "item/recovery_compass_30": [
    480,
    240,
    16,
    16
  ],
  "item/recovery_compass_31": [
    496,
    240,
    16,
    16
  ],
  "item/redstone": [
    0,
    256,
    16,
    16
  ],
  "item/red_candle": [
    16,
    256,
    16,
    16
  ],
  "item/red_dye": [
    32,
    256,
    16,
    16
  ],
  "item/repeater": [
    48,
    256,
    16,
    16
  ],
  "item/rib_armor_trim_smithing_template": [
    64,
    256,
    16,
    16
  ],
  "item/rotten_flesh": [
    80,
    256,
    16,
    16
  ],
  "item/saddle": [
    96,
    256,
    16,
    16
  ],
  "item/salmon": [
    112,
    256,
    16,
    16
  ],
  "item/salmon_bucket": [
    128,
    256,
    16,
    16
  ],
  "item/scrape_pottery_sherd": [
    144,
    256,
    16,
    16
  ],
  "item/seagrass": [
    160,
    256,
    16,
    16
  ],
  "item/sea_pickle": [
    176,
    256,
    16,
    16
  ],
  "item/sentry_armor_trim_smithing_template": [
    192,
    256,
    16,
    16
  ],
  "item/shaper_armor_trim_smithing_template": [
    208,
    256,
    16,
    16
  ],
  "item/sheaf_pottery_sherd": [
    224,
    256,
    16,
    16
  ],
  "item/shears": [
    240,
    256,
    16,
    16
  ],
  "item/shelter_pottery_sherd": [
    256,
    256,
    16,
    16
  ],
  "item/shulker_shell": [
    272,
    256,
    16,
    16
  ],
  "item/silence_armor_trim_smithing_template": [
    288,
    256,
    16,
    16
  ],
  "item/skull_banner_pattern": [
    304,
    256,
    16,
    16
  ],
  "item/skull_pottery_sherd": [
    320,
    256,
    16,
    16
  ],
  "item/slime_ball": [
    336,
    256,
    16,
    16
  ],
  "item/sniffer_egg": [
    352,
    256,
    16,
    16
  ],
  "item/snort_pottery_sherd": [
    368,
    256,
    16,
    16
  ],
  "item/snout_armor_trim_smithing_template": [
    384,
    256,
    16,
    16
  ],
  "item/snowball": [
    400,
    256,
    16,
    16
  ],
  "item/soul_campfire": [
    416,
    256,
    16,
    16
  ],
  "item/soul_lantern": [
    432,
    256,
    16,
    16
  ],
  "item/spawn_egg": [
    448,
    256,
    16,
    16
  ],
  "item/spawn_egg_overlay": [
    464,
    256,
    16,
    16
  ],
  "item/spectral_arrow": [
    480,
    256,
    16,
    16
  ],
  "item/spider_eye": [
    496,
    256,
    16,
    16
  ],
  "item/spire_armor_trim_smithing_template": [
    0,
    272,
    16,
    16
  ],
  "item/splash_potion": [
    16,
    272,
    16,
    16
  ],
  "item/spruce_boat": [
    32,
    272,
    16,
    16
  ],
  "item/spruce_chest_boat": [
    48,
    272,
    16,
    16
  ],
  "item/spruce_door": [
    64,
    272,
    16,
    16
  ],
  "item/spruce_hanging_sign": [
    80,
    272,
    16,
    16
  ],
  "item/spruce_sign": [
    96,
    272,
    16,
    16
  ],
  "item/spyglass": [
    112,
    272,
    16,
    16
  ],
  "item/spyglass_model": [
    128,
    272,
    16,
    16
  ],
  "item/stick": [
    144,
    272,
    16,
    16
  ],
  "item/stone_axe": [
    160,
    272,
    16,
    16
  ],
  "item/stone_hoe": [
    176,
    272,
    16,
    16
  ],
  "item/stone_pickaxe": [
    192,
    272,
    16,
    16
  ],
  "item/stone_shovel": [
    208,
    272,
    16,
    16
  ],
  "item/stone_sword": [
    224,
    272,
    16,
    16
  ],
  "item/string": [
    240,
    272,
    16,
    16
  ],
  "item/structure_void": [
    256,
    272,
    16,
    16
  ],
  "item/sugar": [
    272,
    272,
    16,
    16
  ],
  "item/sugar_cane": [
    288,
    272,
    16,
    16
  ],
  "item/suspicious_stew": [
    304,
    272,
    16,
    16
  ],
  "item/sweet_berries": [
    320,
    272,
    16,
    16
  ],
  "item/tadpole_bucket": [
    336,
    272,
    16,
    16
  ],
  "item/tide_armor_trim_smithing_template": [
    352,
    272,
    16,
    16
  ],
  "item/tipped_arrow_base": [
    368,
    272,
    16,
    16
  ],
  "item/tipped_arrow_head": [
    384,
    272,
    16,
    16
  ],
  "item/tnt_minecart": [
    400,
    272,
    16,
    16
  ],
  "item/torchflower_seeds": [
    416,
    272,
    16,
    16
  ],
  "item/totem_of_undying": [
    432,
    272,
    16,
    16
  ],
  "item/trial_key": [
    448,
    272,
    16,
    16
  ],
  "item/trident": [
    464,
    272,
    16,
    16
  ],
  "item/tropical_fish": [
    480,
    272,
    16,
    16
  ],
  "item/tropical_fish_bucket": [
    496,
    272,
    16,
    16
  ],
  "item/turtle_egg": [
    0,
    288,
    16,
    16
  ],
  "item/turtle_helmet": [
    16,
    288,
    16,
    16
  ],
  "item/turtle_scute": [
    32,
    288,
    16,
    16
  ],
  "item/vex_armor_trim_smithing_template": [
    48,
    288,
    16,
    16
  ],
  "item/ward_armor_trim_smithing_template": [
    64,
    288,
    16,
    16
  ],
  "item/warped_door": [
    80,
    288,
    16,
    16
  ],
  "item/warped_fungus_on_a_stick": [
    96,
    288,
    16,
    16
  ],
  "item/warped_hanging_sign": [
    112,
    288,
    16,
    16
  ],
  "item/warped_sign": [
    128,
    288,
    16,
    16
  ],
  "item/water_bucket": [
    144,
    288,
    16,
    16
  ],
  "item/wayfinder_armor_trim_smithing_template": [
    160,
    288,
    16,
    16
  ],
  "item/weathered_copper_door": [
    176,
    288,
    16,
    16
  ],
  "item/wheat": [
    192,
    288,
    16,
    16
  ],
  "item/wheat_seeds": [
    208,
    288,
    16,
    16
  ],
  "item/white_candle": [
    224,
    288,
    16,
    16
  ],
  "item/white_dye": [
    240,
    288,
    16,
    16
  ],
  "item/wild_armor_trim_smithing_template": [
    256,
    288,
    16,
    16
  ],
  "item/wind_charge": [
    272,
    288,
    16,
    16
  ],
  "item/wolf_armor": [
    288,
    288,
    16,
    16
  ],
  "item/wolf_armor_overlay": [
    304,
    288,
    16,
    16
  ],
  "item/wooden_axe": [
    320,
    288,
    16,
    16
  ],
  "item/wooden_hoe": [
    336,
    288,
    16,
    16
  ],
  "item/wooden_pickaxe": [
    352,
    288,
    16,
    16
  ],
  "item/wooden_shovel": [
    368,
    288,
    16,
    16
  ],
  "item/wooden_sword": [
    384,
    288,
    16,
    16
  ],
  "item/writable_book": [
    400,
    288,
    16,
    16
  ],
  "item/written_book": [
    416,
    288,
    16,
    16
  ],
  "item/yellow_candle": [
    432,
    288,
    16,
    16
  ],
  "item/yellow_dye": [
    448,
    288,
    16,
    16
  ]
}
